Workbook

Sheet Leia-me
A1: Revisão jurídica do jogo Cidade Legal (Educa Direito)
A2: Conteúdo extraído do jogo em 29/10/2026: 803 afirmações (aulas, perguntas, casos, audiências, ocorrências, bairros, projetos de lei e eventos).
A4: Como revisar
A5: 1. Na aba "Revisão", leia o texto e a base legal citada.
A6: 2. Preencha apenas as colunas com fundo amarelo: Status, Correção sugerida, Revisado por e Data.
A7: 3. Status: "Correto", "Corrigir" (há erro), "Desatualizado" (a lei mudou) ou "Simplificar/esclarecer". Deixe "A revisar" enquanto não olhar.
A8: 4. Comece pelas linhas com Prioridade "Alta" (definem a resposta certa do jogo) e pelas marcadas na coluna "Atenção".
A9: 5. A aba "Resumo" atualiza sozinha o andamento da revisão.
A11: Exemplo de preenchimento
A12: Status: Corrigir · Correção sugerida: "O prazo é de 30 dias, não 15 (CDC, art. 18, §1º)" · Revisado por: Dra. Ana Lima · Data: 05/11/2026
A14: Depois da revisão, envie a planilha de volta ao Claude para aplicar as correções no jogo.
A15: Conteúdo educativo e simplificado: não substitui orientação jurídica profissional.

Sheet Revisão
A1: ID | B1: Onde no jogo | C1: Área do Direito | D1: Tipo | E1: Texto / afirmação | F1: Base legal citada | G1: Prioridade | H1: Atenção | I1: Status | J1: Correção sugerida | K1: Revisado por | L1: Data
A2: R001 | B2: Prefeitura › Aula | C2: Direito Constitucional e Administrativo | D2: Resumo da aula | E2: O município é um ente da federação com autonomia: tem prefeito, vereadores e leis próprias para assuntos de interesse local. | G2: Média | I2: A revisar
A3: R002 | B3: Prefeitura › Aula, ponto 1 | C3: Direito Constitucional e Administrativo | D3: Ponto da aula | E3: O Brasil é uma federação formada pela União, Estados, Distrito Federal e Municípios — todos autônomos (CF, art. 18). | F3: CF, art. 18 | G3: Média | I3: A revisar
A4: R003 | B4: Prefeitura › Aula, ponto 2 | C4: Direito Constitucional e Administrativo | D4: Ponto da aula | E4: O município legisla sobre assuntos de interesse local, como coleta de lixo, transporte urbano e uso do solo (CF, art. 30). | F4: CF, art. 30 | G4: Média | I4: A revisar
A5: R004 | B5: Prefeitura › Aula, ponto 3 | C5: Direito Constitucional e Administrativo | D5: Ponto da aula | E5: A administração pública segue o "LIMPE": Legalidade, Impessoalidade, Moralidade, Publicidade e Eficiência (CF, art. 37). | F5: CF, art. 37 | G5: Média | I5: A revisar
A6: R005 | B6: Prefeitura › Aula, ponto 4 | C6: Direito Constitucional e Administrativo | D6: Ponto da aula | E6: Para contratar obras e serviços, a prefeitura faz licitação (Lei 14.133/2021); para contratar servidores efetivos, concurso público (CF, art. 37, II). | F6: CF, art. 37, II | G6: Média | I6: A revisar
A7: R006 | B7: Prefeitura › Aula, na prática | C7: Direito Constitucional e Administrativo | D7: Exemplo prático | E7: O prefeito não pode contratar a empresa do primo sem licitação, nem nomear o filho para um cargo efetivo sem concurso. | G7: Média | I7: A revisar
A8: R007 | B8: Casas › Aula | C8: Direito Civil — Propriedade | D8: Resumo da aula | E8: A propriedade dá ao dono o direito de usar, aproveitar, vender e reaver o bem — mas ela deve cumprir sua função social. | G8: Média | I8: A revisar
A9: R008 | B9: Casas › Aula, ponto 1 | C9: Direito Civil — Propriedade | D9: Ponto da aula | E9: O proprietário pode usar, gozar, dispor e reaver a coisa de quem a possua injustamente (Código Civil, art. 1.228). | F9: Código Civil, art. 1.228 | G9: Média | I9: A revisar
A10: R009 | B10: Casas › Aula, ponto 2 | C10: Direito Civil — Propriedade | D10: Ponto da aula | E10: Imóvel só passa a ser seu com o registro da escritura no Cartório de Registro de Imóveis (CC, art. 1.245). "Contrato de gaveta" não transfere a propriedade. | G10: Média | I10: A revisar
A11: R010 | B11: Casas › Aula, ponto 3 | C11: Direito Civil — Propriedade | D11: Ponto da aula | E11: Usucapião: quem mora num imóvel urbano de até 250 m², por 5 anos, sem oposição e sem ter outro imóvel, pode se tornar dono (CF, art. 183). | F11: CF, art. 183 | G11: Média | I11: A revisar
A12: R011 | B12: Casas › Aula, ponto 4 | C12: Direito Civil — Propriedade | D12: Ponto da aula | E12: Imóveis públicos não podem ser adquiridos por usucapião (CF, art. 183, §3º). | F12: CF, art. 183, §3º | G12: Média | I12: A revisar
A13: R012 | B13: Casas › Aula, ponto 5 | C13: Direito Civil — Propriedade | D13: Ponto da aula | E13: O vizinho não pode fazer uso anormal da propriedade que prejudique o sossego, a saúde ou a segurança dos outros (CC, art. 1.277). | F13: CC, art. 1.277 | G13: Média | I13: A revisar
A14: R013 | B14: Casas › Aula, na prática | C14: Direito Civil — Propriedade | D14: Exemplo prático | E14: Comprou uma casa? Faça a escritura e registre no Cartório de Imóveis. Sem registro, o vendedor ainda é o dono no papel. | G14: Média | I14: A revisar
A15: R014 | B15: Casas › Prova, pergunta 1 | C15: Direito Civil — Propriedade | D15: Pergunta da prova | E15: Quando a propriedade de um imóvel é transferida ao comprador? → Resposta: Com o registro do título no Cartório de Registro de Imóveis. Pelo art. 1.245 do Código Civil, entre vivos a propriedade imobiliária só se transfere com o registro do título no Registro de Imóveis. | F15: Pelo art. 1.245 do Código Civil, entre vivos a propriedade imobiliária só se transfere com o registro do título no Registro de Imóveis. | G15: Alta | I15: A revisar
A16: R015 | B16: Casas › Prova, pergunta 2 | C16: Direito Civil — Propriedade | D16: Pergunta da prova | E16: Qual o prazo da usucapião especial urbana (imóvel de até 250 m² usado como moradia)? → Resposta: 5 anos. A CF, art. 183, prevê 5 anos de posse ininterrupta e sem oposição, desde que a pessoa não seja dona de outro imóvel. | F16: A CF, art. 183, prevê 5 anos de posse ininterrupta e sem oposição, desde que a pessoa não seja dona de outro imóvel. | G16: Alta | I16: A revisar
A17: R016 | B17: Casas › Prova, pergunta 3 | C17: Direito Civil — Propriedade | D17: Pergunta da prova | E17: É possível adquirir uma praça pública por usucapião? → Resposta: Não, bens públicos não são usucapíveis. A Constituição (art. 183, §3º e art. 191, parágrafo único) proíbe a usucapião de imóveis públicos. | F17: A Constituição (art. 183, §3º e art. 191, parágrafo único) proíbe a usucapião de imóveis públicos. | G17: Alta | I17: A revisar
A18: R017 | B18: Casas › Prova, pergunta 4 | C18: Direito Civil — Propriedade | D18: Pergunta da prova | E18: O vizinho faz festas barulhentas toda madrugada. Qual regra protege você? → Resposta: Direito de vizinhança — uso anormal da propriedade. O art. 1.277 do Código Civil permite ao vizinho fazer cessar interferências prejudiciais ao sossego, à saúde e à segurança. | F18: O art. 1.277 do Código Civil permite ao vizinho fazer cessar interferências prejudiciais ao sossego, à saúde e à segurança. | G18: Alta | I18: A revisar
A19: R018 | B19: Prédio de Aluguel › Aula | C19: Lei do Inquilinato | D19: Resumo da aula | E19: A Lei do Inquilinato (Lei 8.245/1991) regula a relação entre quem aluga (locador) e quem mora (locatário). | G19: Média | I19: A revisar
A20: R019 | B20: Prédio de Aluguel › Aula, ponto 1 | C20: Lei do Inquilinato | D20: Ponto da aula | E20: O locatário pode devolver o imóvel antes do fim do contrato pagando multa proporcional ao tempo que falta (art. 4º). | F20: art. 4º | G20: Média | I20: A revisar
A21: R020 | B21: Prédio de Aluguel › Aula, ponto 2 | C21: Lei do Inquilinato | D21: Ponto da aula | E21: O contrato pode exigir apenas UMA garantia: caução, fiança, seguro-fiança ou cessão fiduciária de quotas (art. 37). Exigir duas é contravenção. | G21: Média | I21: A revisar
A22: R021 | B22: Prédio de Aluguel › Aula, ponto 3 | C22: Lei do Inquilinato | D22: Ponto da aula | E22: A caução em dinheiro não pode passar de 3 meses de aluguel (art. 38, §2º). | F22: art. 38, §2º | G22: Média | I22: A revisar
A23: R022 | B23: Prédio de Aluguel › Aula, ponto 4 | C23: Lei do Inquilinato | D23: Ponto da aula | E23: Se o imóvel for vendido, o inquilino tem direito de preferência para comprá-lo nas mesmas condições (art. 27). | F23: art. 27 | G23: Média | I23: A revisar
A24: R023 | B24: Prédio de Aluguel › Aula, ponto 5 | C24: Lei do Inquilinato | D24: Ponto da aula | E24: O locador deve entregar o imóvel em condições de uso e pagar as despesas extraordinárias de condomínio, como reformas estruturais (art. 22). | F24: art. 22 | G24: Média | I24: A revisar
A25: R024 | B25: Prédio de Aluguel › Aula, na prática | C25: Lei do Inquilinato | D25: Exemplo prático | E25: Pediram fiador E seguro-fiança ao mesmo tempo? Isso é ilegal: a lei só permite uma modalidade de garantia por contrato. | G25: Média | I25: A revisar
A26: R025 | B26: Prédio de Aluguel › Prova, pergunta 1 | C26: Lei do Inquilinato | D26: Pergunta da prova | E26: Quantas modalidades de garantia o locador pode exigir no mesmo contrato? → Resposta: Uma. O parágrafo único do art. 37 da Lei 8.245/91 veda mais de uma modalidade de garantia no mesmo contrato. | F26: O parágrafo único do art. 37 da Lei 8.245/91 veda mais de uma modalidade de garantia no mesmo contrato. | G26: Alta | I26: A revisar
A27: R026 | B27: Prédio de Aluguel › Prova, pergunta 2 | C27: Lei do Inquilinato | D27: Pergunta da prova | E27: Qual o limite da caução em dinheiro? → Resposta: 3 meses de aluguel. O art. 38, §2º, limita a caução em dinheiro a 3 meses de aluguel, depositada em poupança. | F27: O art. 38, §2º, limita a caução em dinheiro a 3 meses de aluguel, depositada em poupança. | G27: Alta | I27: A revisar
A28: R027 | B28: Prédio de Aluguel › Prova, pergunta 3 | C28: Lei do Inquilinato | D28: Pergunta da prova | E28: O dono decide vender o apartamento alugado. O que o inquilino tem? → Resposta: Direito de preferência na compra. O art. 27 da Lei do Inquilinato garante ao locatário a preferência para adquirir o imóvel em igualdade de condições com terceiros. | F28: O art. 27 da Lei do Inquilinato garante ao locatário a preferência para adquirir o imóvel em igualdade de condições com terceiros. | G28: Alta | I28: A revisar
A29: R028 | B29: Mercado › Aula | C29: Direito do Consumidor | D29: Resumo da aula | E29: O Código de Defesa do Consumidor (Lei 8.078/1990) protege quem compra, porque o consumidor é a parte mais fraca da relação. | G29: Média | I29: A revisar
A30: R029 | B30: Mercado › Aula, ponto 1 | C30: Direito do Consumidor | D30: Ponto da aula | E30: Comprou fora da loja (internet, telefone, porta a porta)? Você tem 7 dias para desistir e receber tudo de volta (art. 49). | F30: art. 49 | G30: Média | I30: A revisar
A31: R030 | B31: Mercado › Aula, ponto 2 | C31: Direito do Consumidor | D31: Ponto da aula | E31: Prazo para reclamar de defeito aparente: 30 dias para produtos não duráveis (comida) e 90 dias para duráveis (eletrônicos) (art. 26). | F31: art. 26 | G31: Média | I31: A revisar
A32: R031 | B32: Mercado › Aula, ponto 3 | C32: Direito do Consumidor | D32: Ponto da aula | E32: Venda casada é proibida — a loja não pode obrigar você a levar um produto para comprar outro (art. 39, I). | F32: art. 39, I | G32: Média | I32: A revisar
A33: R032 | B33: Mercado › Aula, ponto 4 | C33: Direito do Consumidor | D33: Ponto da aula | E33: Propaganda enganosa ou abusiva é proibida, e a oferta anunciada obriga o fornecedor (arts. 30 e 37). | G33: Média | I33: A revisar
A34: R033 | B34: Mercado › Aula, ponto 5 | C34: Direito do Consumidor | D34: Ponto da aula | E34: O fornecedor responde pelos danos causados por defeito do produto mesmo sem culpa — é a responsabilidade objetiva (art. 12). | F34: art. 12 | G34: Média | I34: A revisar
A35: R034 | B35: Mercado › Aula, na prática | C35: Direito do Consumidor | D35: Exemplo prático | E35: O preço na etiqueta era menor que o do caixa? A oferta vincula a loja: você paga o menor preço anunciado. | G35: Média | I35: A revisar
A36: R035 | B36: Mercado › Prova, pergunta 1 | C36: Direito do Consumidor | D36: Pergunta da prova | E36: Comprei um tênis pela internet e me arrependi. Qual o prazo para desistir? → Resposta: 7 dias. O direito de arrependimento (art. 49 do CDC) vale por 7 dias para compras fora do estabelecimento comercial. | F36: O direito de arrependimento (art. 49 do CDC) vale por 7 dias para compras fora do estabelecimento comercial. | G36: Alta | I36: A revisar
A37: R036 | B37: Mercado › Prova, pergunta 2 | C37: Direito do Consumidor | D37: Pergunta da prova | E37: O cinema só deixa entrar quem comprar a pipoca dele. Isso é: → Resposta: Venda casada, prática abusiva. Condicionar o fornecimento de um produto ou serviço a outro é venda casada, proibida pelo art. 39, I, do CDC. | F37: Condicionar o fornecimento de um produto ou serviço a outro é venda casada, proibida pelo art. 39, I, do CDC. | G37: Alta | I37: A revisar
A38: R037 | B38: Mercado › Prova, pergunta 3 | C38: Direito do Consumidor | D38: Pergunta da prova | E38: Qual o prazo para reclamar de defeito aparente numa geladeira (produto durável)? → Resposta: 90 dias. Para produtos duráveis o prazo é de 90 dias (art. 26, II, do CDC); para não duráveis, 30 dias. | F38: Para produtos duráveis o prazo é de 90 dias (art. 26, II, do CDC); para não duráveis, 30 dias. | G38: Alta | I38: A revisar
A39: R038 | B39: Mercado › Prova, pergunta 4 | C39: Direito do Consumidor | D39: Pergunta da prova | E39: Um anúncio diz que o celular é à prova d'água, mas não é. Isso é: → Resposta: Propaganda enganosa. Informação falsa capaz de induzir o consumidor a erro é publicidade enganosa (art. 37, §1º, do CDC). | F39: Informação falsa capaz de induzir o consumidor a erro é publicidade enganosa (art. 37, §1º, do CDC). | G39: Alta | I39: A revisar
A40: R039 | B40: Fábrica › Aula | C40: Direito do Trabalho | D40: Resumo da aula | E40: A CLT e o art. 7º da Constituição garantem direitos mínimos a quem trabalha com carteira assinada. | G40: Média | I40: A revisar
A41: R040 | B41: Fábrica › Aula, ponto 1 | C41: Direito do Trabalho | D41: Ponto da aula | E41: Jornada normal de até 8 horas por dia e 44 horas por semana (CF, art. 7º, XIII). O que passar disso é hora extra, paga com no mínimo 50% a mais (art. 7º, XVI). | F41: art. 7º, XVI | G41: Média | I41: A revisar
A42: R041 | B42: Fábrica › Aula, ponto 2 | C42: Direito do Trabalho | D42: Ponto da aula | E42: Férias anuais remuneradas com um terço a mais (art. 7º, XVII) e 13º salário (art. 7º, VIII). | F42: art. 7º, VIII | G42: Média | I42: A revisar
A43: R042 | B43: Fábrica › Aula, ponto 3 | C43: Direito do Trabalho | D43: Ponto da aula | E43: Quem trabalha mais de 6 horas tem direito a no mínimo 1 hora de intervalo para refeição (CLT, art. 71). | F43: CLT, art. 71 | G43: Média | I43: A revisar
A44: R043 | B44: Fábrica › Aula, ponto 4 | C44: Direito do Trabalho | D44: Ponto da aula | E44: O empregador deve recolher o FGTS — 8% do salário depositados todo mês em conta do trabalhador (Lei 8.036/1990). | F44: Lei 8.036/1990 | G44: Média | I44: A revisar
A45: R044 | B45: Fábrica › Aula, ponto 5 | C45: Direito do Trabalho | D45: Ponto da aula | E45: É proibido qualquer trabalho a menores de 16 anos, salvo como aprendiz a partir dos 14 (CF, art. 7º, XXXIII). | F45: CF, art. 7º, XXXIII | G45: Média | I45: A revisar
A46: R045 | B46: Fábrica › Aula, na prática | C46: Direito do Trabalho | D46: Exemplo prático | E46: Trabalhou 10 horas num dia? As 2 horas a mais são extras e devem ser pagas com adicional de pelo menos 50% (ou compensadas em banco de horas válido). | G46: Média | I46: A revisar
A47: R046 | B47: Fábrica › Prova, pergunta 1 | C47: Direito do Trabalho | D47: Pergunta da prova | E47: Qual a jornada máxima normal prevista na Constituição? → Resposta: 8h/dia e 44h/semana. O art. 7º, XIII, da CF fixa duração do trabalho normal não superior a 8 horas diárias e 44 semanais. | F47: O art. 7º, XIII, da CF fixa duração do trabalho normal não superior a 8 horas diárias e 44 semanais. | G47: Alta | I47: A revisar
A48: R047 | B48: Fábrica › Prova, pergunta 2 | C48: Direito do Trabalho | D48: Pergunta da prova | E48: Qual o adicional mínimo da hora extra? → Resposta: 50%. O art. 7º, XVI, da CF garante remuneração do serviço extraordinário superior, no mínimo, em 50% à do normal. | F48: O art. 7º, XVI, da CF garante remuneração do serviço extraordinário superior, no mínimo, em 50% à do normal. | G48: Alta | I48: A revisar
A49: R048 | B49: Fábrica › Prova, pergunta 3 | C49: Direito do Trabalho | D49: Pergunta da prova | E49: A partir de que idade alguém pode trabalhar como aprendiz? → Resposta: 14 anos. A CF (art. 7º, XXXIII) proíbe trabalho a menores de 16 anos, salvo na condição de aprendiz, a partir de 14. | F49: A CF (art. 7º, XXXIII) proíbe trabalho a menores de 16 anos, salvo na condição de aprendiz, a partir de 14. | G49: Alta | I49: A revisar
A50: R049 | B50: Fábrica › Prova, pergunta 4 | C50: Direito do Trabalho | D50: Pergunta da prova | E50: Além do salário, quanto o trabalhador recebe a mais nas férias? → Resposta: Um terço do salário. As férias são remuneradas com, pelo menos, um terço a mais do que o salário normal (CF, art. 7º, XVII). | F50: As férias são remuneradas com, pelo menos, um terço a mais do que o salário normal (CF, art. 7º, XVII). | G50: Alta | I50: A revisar
A51: R050 | B51: Escola › Aula | C51: Educação e ECA | D51: Resumo da aula | E51: Crianças e adolescentes têm prioridade absoluta. Educação é direito de todos e dever do Estado e da família. | G51: Média | I51: A revisar
A52: R051 | B52: Escola › Aula, ponto 1 | C52: Educação e ECA | D52: Ponto da aula | E52: Para o ECA (Lei 8.069/1990), criança é quem tem até 12 anos incompletos; adolescente, de 12 a 18 anos (art. 2º). | F52: art. 2º | G52: Média | I52: A revisar
A53: R052 | B53: Escola › Aula, ponto 2 | C53: Educação e ECA | D53: Ponto da aula | E53: Família, sociedade e poder público devem garantir, com prioridade absoluta, os direitos de crianças e adolescentes (CF, art. 227; ECA, art. 4º). | F53: CF, art. 227; ECA, art. 4º | G53: Média | I53: A revisar
A54: R053 | B54: Escola › Aula, ponto 3 | C54: Educação e ECA | D54: Ponto da aula | E54: A educação básica é obrigatória e gratuita dos 4 aos 17 anos (CF, art. 208, I). | F54: CF, art. 208, I | G54: Média | I54: A revisar
A55: R054 | B55: Escola › Aula, ponto 4 | C55: Educação e ECA | D55: Ponto da aula | E55: Todo município deve ter ao menos um Conselho Tutelar, com 5 membros escolhidos pela comunidade (ECA, art. 132). | F55: ECA, art. 132 | G55: Média | I55: A revisar
A56: R055 | B56: Escola › Aula, ponto 5 | C56: Educação e ECA | D56: Ponto da aula | E56: A escola deve comunicar ao Conselho Tutelar casos de maus-tratos e de faltas reiteradas dos alunos (ECA, arts. 13 e 56). | F56: ECA, arts. 13 e 56 | G56: Média | I56: A revisar
A57: R056 | B57: Escola › Aula, na prática | C57: Educação e ECA | D57: Exemplo prático | E57: Um aluno parou de ir à aula e a família não responde? A escola aciona o Conselho Tutelar, que acompanha o caso. | G57: Média | I57: A revisar
A58: R057 | B58: Escola › Prova, pergunta 1 | C58: Educação e ECA | D58: Pergunta da prova | E58: Pelo ECA, até que idade uma pessoa é considerada criança? → Resposta: Até 12 anos incompletos. O art. 2º do ECA define criança como a pessoa até 12 anos incompletos e adolescente entre 12 e 18 anos. | F58: O art. 2º do ECA define criança como a pessoa até 12 anos incompletos e adolescente entre 12 e 18 anos. | G58: Alta | I58: A revisar
A59: R058 | B59: Escola › Prova, pergunta 2 | C59: Educação e ECA | D59: Pergunta da prova | E59: Dos quantos aos quantos anos a educação básica é obrigatória? → Resposta: 4 a 17 anos. Pela CF, art. 208, I (EC 59/2009), a educação básica é obrigatória e gratuita dos 4 aos 17 anos. | F59: Pela CF, art. 208, I (EC 59/2009), a educação básica é obrigatória e gratuita dos 4 aos 17 anos. | G59: Alta | I59: A revisar
A60: R059 | B60: Escola › Prova, pergunta 3 | C60: Educação e ECA | D60: Pergunta da prova | E60: Quem a escola deve avisar em caso de suspeita de maus-tratos a um aluno? → Resposta: O Conselho Tutelar. O art. 56 do ECA obriga os dirigentes de escolas a comunicar ao Conselho Tutelar os casos de maus-tratos. | F60: O art. 56 do ECA obriga os dirigentes de escolas a comunicar ao Conselho Tutelar os casos de maus-tratos. | G60: Alta | I60: A revisar
A61: R060 | B61: Posto de Saúde › Aula | C61: Direito à Saúde (SUS) | D61: Resumo da aula | E61: Saúde é direito de todos e dever do Estado. O SUS (Lei 8.080/1990) atende qualquer pessoa, de graça. | G61: Média | I61: A revisar
A62: R061 | B62: Posto de Saúde › Aula, ponto 1 | C62: Direito à Saúde (SUS) | D62: Ponto da aula | E62: A saúde é direito de todos e dever do Estado (CF, art. 196). | F62: CF, art. 196 | G62: Média | I62: A revisar
A63: R062 | B63: Posto de Saúde › Aula, ponto 2 | C63: Direito à Saúde (SUS) | D63: Ponto da aula | E63: O SUS é universal: atende todas as pessoas, inclusive estrangeiros, sem exigir pagamento (Lei 8.080/90, art. 7º, I). | F63: Lei 8.080/90, art. 7º, I | G63: Média | I63: A revisar
A64: R063 | B64: Posto de Saúde › Aula, ponto 3 | C64: Direito à Saúde (SUS) | D64: Ponto da aula | E64: O SUS é descentralizado: União, Estados e Municípios dividem as responsabilidades, e o município cuida da atenção básica. | G64: Média | I64: A revisar
A65: R064 | B65: Posto de Saúde › Aula, ponto 4 | C65: Direito à Saúde (SUS) | D65: Ponto da aula | E65: O paciente tem direito de acesso ao próprio prontuário e às informações sobre seu tratamento. | G65: Média | I65: A revisar
A66: R065 | B66: Posto de Saúde › Aula, na prática | C66: Direito à Saúde (SUS) | D66: Exemplo prático | E66: Um turista estrangeiro passou mal na cidade? O posto de saúde deve atendê-lo normalmente: o SUS é universal. | G66: Média | I66: A revisar
A67: R066 | B67: Posto de Saúde › Prova, pergunta 1 | C67: Direito à Saúde (SUS) | D67: Pergunta da prova | E67: Segundo a Constituição, a saúde é: → Resposta: Direito de todos e dever do Estado. É o que diz o art. 196 da Constituição Federal. | F67: É o que diz o art. 196 da Constituição Federal. | G67: Alta | I67: A revisar
A68: R067 | B68: Posto de Saúde › Prova, pergunta 2 | C68: Direito à Saúde (SUS) | D68: Pergunta da prova | E68: Quem pode ser atendido pelo SUS? → Resposta: Qualquer pessoa. A universalidade de acesso é princípio do SUS (Lei 8.080/90, art. 7º, I). | F68: A universalidade de acesso é princípio do SUS (Lei 8.080/90, art. 7º, I). | G68: Alta | I68: A revisar
A69: R068 | B69: Posto de Saúde › Prova, pergunta 3 | C69: Direito à Saúde (SUS) | D69: Pergunta da prova | E69: Qual lei organiza o Sistema Único de Saúde? → Resposta: Lei 8.080/1990. A Lei 8.080/90 é a Lei Orgânica da Saúde. (A 8.078/90 é o CDC — números parecidos, assuntos diferentes!) | F69: A Lei 8.080/90 é a Lei Orgânica da Saúde. (A 8.078/90 é o CDC — números parecidos, assuntos diferentes!) | G69: Alta | I69: A revisar
A70: R069 | B70: Parque › Aula | C70: Direito Ambiental | D70: Resumo da aula | E70: Todos têm direito a um meio ambiente equilibrado, e todos — governo e sociedade — devem protegê-lo para as futuras gerações. | G70: Média | I70: A revisar
A71: R070 | B71: Parque › Aula, ponto 1 | C71: Direito Ambiental | D71: Ponto da aula | E71: O meio ambiente ecologicamente equilibrado é bem de uso comum do povo (CF, art. 225). | F71: CF, art. 225 | G71: Média | I71: A revisar
A72: R071 | B72: Parque › Aula, ponto 2 | C72: Direito Ambiental | D72: Ponto da aula | E72: Quem polui deve reparar o dano, independentemente de culpa — responsabilidade objetiva (Lei 6.938/1981, art. 14, §1º). | F72: Lei 6.938/1981, art. 14, §1º | G72: Média | I72: A revisar
A73: R072 | B73: Parque › Aula, ponto 3 | C73: Direito Ambiental | D73: Ponto da aula | E73: A Lei de Crimes Ambientais (Lei 9.605/1998) pune também empresas, não só pessoas físicas. | G73: Média | I73: A revisar
A74: R073 | B74: Parque › Aula, ponto 4 | C74: Direito Ambiental | D74: Ponto da aula | E74: As margens de rios são Áreas de Preservação Permanente (APP): no mínimo 30 metros para rios de até 10 m de largura (Código Florestal, Lei 12.651/2012, art. 4º). | F74: Código Florestal, Lei 12.651/2012, art. 4º | G74: Média | I74: A revisar
A75: R074 | B75: Parque › Aula, na prática | C75: Direito Ambiental | D75: Exemplo prático | E75: Uma fábrica jogou resíduos no rio "sem querer"? Ela responde mesmo assim: no dano ambiental, não importa a culpa. | G75: Média | I75: A revisar
A76: R075 | B76: Parque › Prova, pergunta 1 | C76: Direito Ambiental | D76: Pergunta da prova | E76: Uma empresa poluiu um rio por acidente, sem culpa. Ela deve reparar o dano? → Resposta: Sim, a responsabilidade ambiental é objetiva. Pela Lei 6.938/81, art. 14, §1º, o poluidor deve reparar o dano independentemente de culpa. | F76: Pela Lei 6.938/81, art. 14, §1º, o poluidor deve reparar o dano independentemente de culpa. | G76: Alta | I76: A revisar
A77: R076 | B77: Parque › Prova, pergunta 2 | C77: Direito Ambiental | D77: Pergunta da prova | E77: Empresas podem responder por crimes ambientais? → Resposta: Sim, pela Lei 9.605/1998 e pela CF, art. 225, §3º. A Constituição (art. 225, §3º) e a Lei 9.605/98 (art. 3º) admitem a responsabilização penal da pessoa jurídica. | F77: A Constituição (art. 225, §3º) e a Lei 9.605/98 (art. 3º) admitem a responsabilização penal da pessoa jurídica. | G77: Alta | I77: A revisar
A78: R077 | B78: Parque › Prova, pergunta 3 | C78: Direito Ambiental | D78: Pergunta da prova | E78: Qual a faixa mínima de mata a preservar na margem de um riacho com menos de 10 m de largura? → Resposta: 30 metros. O Código Florestal (art. 4º, I, "a") fixa APP de 30 metros para cursos d'água com menos de 10 metros de largura. | F78: O Código Florestal (art. 4º, I, "a") fixa APP de 30 metros para cursos d'água com menos de 10 metros de largura. | G78: Alta | I78: A revisar
A79: R078 | B79: Delegacia › Aula | C79: Direito Penal e Processo Penal | D79: Resumo da aula | E79: Só é crime o que a lei define como crime, e mesmo o suspeito tem direitos garantidos pela Constituição. | G79: Média | I79: A revisar
A80: R079 | B80: Delegacia › Aula, ponto 1 | C80: Direito Penal e Processo Penal | D80: Ponto da aula | E80: Não há crime sem lei anterior que o defina, nem pena sem prévia cominação legal — princípio da legalidade (CF, art. 5º, XXXIX; Código Penal, art. 1º). | F80: CF, art. 5º, XXXIX; Código Penal, art. 1º | G80: Média | I80: A revisar
A81: R080 | B81: Delegacia › Aula, ponto 2 | C81: Direito Penal e Processo Penal | D81: Ponto da aula | E81: Legítima defesa: não é crime repelir agressão injusta, atual ou iminente, usando moderadamente os meios necessários (CP, art. 25). | F81: CP, art. 25 | G81: Média | I81: A revisar
A82: R081 | B82: Delegacia › Aula, ponto 3 | C82: Direito Penal e Processo Penal | D82: Ponto da aula | E82: O preso tem direito de permanecer calado e de ter assistência de advogado e da família (CF, art. 5º, LXIII). | F82: CF, art. 5º, LXIII | G82: Média | I82: A revisar
A83: R082 | B83: Delegacia › Aula, ponto 4 | C83: Direito Penal e Processo Penal | D83: Ponto da aula | E83: Quem é preso em flagrante deve ser levado a um juiz em até 24 horas — a audiência de custódia (CPP, art. 310). | F83: CPP, art. 310 | G83: Média | I83: A revisar
A84: R083 | B84: Delegacia › Aula, ponto 5 | C84: Direito Penal e Processo Penal | D84: Ponto da aula | E84: Ninguém será considerado culpado até o trânsito em julgado da sentença penal condenatória (CF, art. 5º, LVII). | F84: CF, art. 5º, LVII | G84: Média | I84: A revisar
A85: R084 | B85: Delegacia › Aula, na prática | C85: Direito Penal e Processo Penal | D85: Exemplo prático | E85: Uma lei nova criou um crime hoje. Quem fez aquilo ontem não pode ser punido: a lei penal não retroage para prejudicar. | G85: Média | I85: A revisar
A86: R085 | B86: Delegacia › Prova, pergunta 1 | C86: Direito Penal e Processo Penal | D86: Pergunta da prova | E86: Uma conduta pode ser punida como crime se não havia lei definindo-a quando foi praticada? → Resposta: Não, pelo princípio da legalidade. CF, art. 5º, XXXIX e CP, art. 1º: não há crime sem lei anterior que o defina. | F86: CF, art. 5º, XXXIX e CP, art. 1º: não há crime sem lei anterior que o defina. | G86: Alta | I86: A revisar
A87: R086 | B87: Delegacia › Prova, pergunta 2 | C87: Direito Penal e Processo Penal | D87: Pergunta da prova | E87: Em quanto tempo o preso em flagrante deve ser apresentado ao juiz? → Resposta: 24 horas. O art. 310 do CPP prevê a audiência de custódia em até 24 horas após a prisão. | F87: O art. 310 do CPP prevê a audiência de custódia em até 24 horas após a prisão. | G87: Alta | I87: A revisar
A88: R087 | B88: Delegacia › Prova, pergunta 3 | C88: Direito Penal e Processo Penal | D88: Pergunta da prova | E88: O que é legítima defesa? → Resposta: Repelir agressão injusta, atual ou iminente, com meios moderados. É a definição do art. 25 do Código Penal. Reagir com excesso ou depois que a agressão acabou não é legítima defesa. | F88: É a definição do art. 25 do Código Penal. Reagir com excesso ou depois que a agressão acabou não é legítima defesa. | G88: Alta | I88: A revisar
A89: R088 | B89: Delegacia › Prova, pergunta 4 | C89: Direito Penal e Processo Penal | D89: Pergunta da prova | E89: Ao ser preso, a pessoa: → Resposta: Tem direito de permanecer calada. A CF, art. 5º, LXIII, garante ao preso o direito ao silêncio e à assistência da família e de advogado. | F89: A CF, art. 5º, LXIII, garante ao preso o direito ao silêncio e à assistência da família e de advogado. | G89: Alta | I89: A revisar
A90: R089 | B90: Fórum › Aula | C90: Acesso à Justiça | D90: Resumo da aula | E90: Toda lesão ou ameaça a direito pode ser levada ao Judiciário — e há caminhos simples e gratuitos para isso. | G90: Média | I90: A revisar
A91: R090 | B91: Fórum › Aula, ponto 1 | C91: Acesso à Justiça | D91: Ponto da aula | E91: A lei não pode impedir ninguém de levar seu problema ao Judiciário — inafastabilidade da jurisdição (CF, art. 5º, XXXV). | F91: CF, art. 5º, XXXV | G91: Média | I91: A revisar
A92: R091 | B92: Fórum › Aula, ponto 2 | C92: Acesso à Justiça | D92: Ponto da aula | E92: Os Juizados Especiais Cíveis julgam causas de até 40 salários mínimos de forma simples e rápida (Lei 9.099/1995, art. 3º). | F92: Lei 9.099/1995, art. 3º | G92: Média | I92: A revisar
A93: R092 | B93: Fórum › Aula, ponto 3 | C93: Acesso à Justiça | D93: Ponto da aula | E93: Nos Juizados, em causas de até 20 salários mínimos, você pode entrar sem advogado (art. 9º). | F93: art. 9º | G93: Média | I93: A revisar
A94: R093 | B94: Fórum › Aula, ponto 4 | C94: Acesso à Justiça | D94: Ponto da aula | E94: Quem não pode pagar tem direito à assistência jurídica gratuita, prestada pela Defensoria Pública (CF, arts. 5º, LXXIV e 134). | F94: CF, arts. 5º, LXXIV e 134 | G94: Média | I94: A revisar
A95: R094 | B95: Fórum › Aula, na prática | C95: Acesso à Justiça | D95: Exemplo prático | E95: A loja não quer trocar um celular de R$ 1.500? Você pode ir sozinho ao Juizado Especial Cível e entrar com o pedido. | G95: Média | I95: A revisar
A96: R095 | B96: Fórum › Prova, pergunta 1 | C96: Acesso à Justiça | D96: Pergunta da prova | E96: Até qual valor de causa os Juizados Especiais Cíveis estaduais julgam? → Resposta: 40 salários mínimos. O art. 3º, I, da Lei 9.099/95 fixa o limite de 40 salários mínimos. | F96: O art. 3º, I, da Lei 9.099/95 fixa o limite de 40 salários mínimos. | G96: Alta | I96: A revisar
A97: R096 | B97: Fórum › Prova, pergunta 2 | C97: Acesso à Justiça | D97: Pergunta da prova | E97: Em que situação é possível entrar no Juizado sem advogado? → Resposta: Em causas de até 20 salários mínimos. Pelo art. 9º da Lei 9.099/95, até 20 salários mínimos a assistência por advogado é facultativa. | F97: Pelo art. 9º da Lei 9.099/95, até 20 salários mínimos a assistência por advogado é facultativa. | G97: Alta | I97: A revisar
A98: R097 | B98: Fórum › Prova, pergunta 3 | C98: Acesso à Justiça | D98: Pergunta da prova | E98: Quem presta assistência jurídica gratuita a quem não pode pagar advogado? → Resposta: A Defensoria Pública. A Defensoria Pública é a instituição incumbida da orientação jurídica e defesa dos necessitados (CF, art. 134). | F98: A Defensoria Pública é a instituição incumbida da orientação jurídica e defesa dos necessitados (CF, art. 134). | G98: Alta | I98: A revisar
A99: R098 | B99: Câmara Municipal › Aula | C99: Processo Legislativo | D99: Resumo da aula | E99: Os vereadores fazem as leis da cidade; o prefeito as executa e pode sancionar ou vetar os projetos aprovados. | G99: Média | I99: A revisar
A100: R099 | B100: Câmara Municipal › Aula, ponto 1 | C100: Processo Legislativo | D100: Ponto da aula | E100: O município é regido por uma Lei Orgânica, votada em dois turnos e aprovada por 2/3 dos vereadores (CF, art. 29). | F100: CF, art. 29 | G100: Média | I100: A revisar
...

Sheet Resumo
A1: Andamento da revisão
A3: Tipo | B3: A revisar | C3: Correto | D3: Corrigir | E3: Desatualizado | F3: Simplificar/esclarecer | G3: Total | H3: % revisado
A4: Ponto da aula | B4: =COUNTIFS(Revisão!$D$2:$D$804,$A4,Revisão!$I$2:$I$804,B$3) -> 286 | C4: =COUNTIFS(Revisão!$D$2:$D$804,$A4,Revisão!$I$2:$I$804,C$3) -> 0 | D4: =COUNTIFS(Revisão!$D$2:$D$804,$A4,Revisão!$I$2:$I$804,D$3) -> 0 | E4: =COUNTIFS(Revisão!$D$2:$D$804,$A4,Revisão!$I$2:$I$804,E$3) -> 0 | F4: =COUNTIFS(Revisão!$D$2:$D$804,$A4,Revisão!$I$2:$I$804,F$3) -> 0 | G4: =COUNTIF(Revisão!$D$2:$D$804,$A4) -> 286 | H4: =IF(G4=0,0,1-B4/G4) -> 0
A5: Pergunta da prova | B5: =COUNTIFS(Revisão!$D$2:$D$804,$A5,Revisão!$I$2:$I$804,B$3) -> 202 | C5: =COUNTIFS(Revisão!$D$2:$D$804,$A5,Revisão!$I$2:$I$804,C$3) -> 0 | D5: =COUNTIFS(Revisão!$D$2:$D$804,$A5,Revisão!$I$2:$I$804,D$3) -> 0 | E5: =COUNTIFS(Revisão!$D$2:$D$804,$A5,Revisão!$I$2:$I$804,E$3) -> 0 | F5: =COUNTIFS(Revisão!$D$2:$D$804,$A5,Revisão!$I$2:$I$804,F$3) -> 0 | G5: =COUNTIF(Revisão!$D$2:$D$804,$A5) -> 202 | H5: =IF(G5=0,0,1-B5/G5) -> 0
A6: Caso de cidadão | B6: =COUNTIFS(Revisão!$D$2:$D$804,$A6,Revisão!$I$2:$I$804,B$3) -> 129 | C6: =COUNTIFS(Revisão!$D$2:$D$804,$A6,Revisão!$I$2:$I$804,C$3) -> 0 | D6: =COUNTIFS(Revisão!$D$2:$D$804,$A6,Revisão!$I$2:$I$804,D$3) -> 0 | E6: =COUNTIFS(Revisão!$D$2:$D$804,$A6,Revisão!$I$2:$I$804,E$3) -> 0 | F6: =COUNTIFS(Revisão!$D$2:$D$804,$A6,Revisão!$I$2:$I$804,F$3) -> 0 | G6: =COUNTIF(Revisão!$D$2:$D$804,$A6) -> 129 | H6: =IF(G6=0,0,1-B6/G6) -> 0
A7: Exemplo prático | B7: =COUNTIFS(Revisão!$D$2:$D$804,$A7,Revisão!$I$2:$I$804,B$3) -> 67 | C7: =COUNTIFS(Revisão!$D$2:$D$804,$A7,Revisão!$I$2:$I$804,C$3) -> 0 | D7: =COUNTIFS(Revisão!$D$2:$D$804,$A7,Revisão!$I$2:$I$804,D$3) -> 0 | E7: =COUNTIFS(Revisão!$D$2:$D$804,$A7,Revisão!$I$2:$I$804,E$3) -> 0 | F7: =COUNTIFS(Revisão!$D$2:$D$804,$A7,Revisão!$I$2:$I$804,F$3) -> 0 | G7: =COUNTIF(Revisão!$D$2:$D$804,$A7) -> 67 | H7: =IF(G7=0,0,1-B7/G7) -> 0
A8: Resumo da aula | B8: =COUNTIFS(Revisão!$D$2:$D$804,$A8,Revisão!$I$2:$I$804,B$3) -> 67 | C8: =COUNTIFS(Revisão!$D$2:$D$804,$A8,Revisão!$I$2:$I$804,C$3) -> 0 | D8: =COUNTIFS(Revisão!$D$2:$D$804,$A8,Revisão!$I$2:$I$804,D$3) -> 0 | E8: =COUNTIFS(Revisão!$D$2:$D$804,$A8,Revisão!$I$2:$I$804,E$3) -> 0 | F8: =COUNTIFS(Revisão!$D$2:$D$804,$A8,Revisão!$I$2:$I$804,F$3) -> 0 | G8: =COUNTIF(Revisão!$D$2:$D$804,$A8) -> 67 | H8: =IF(G8=0,0,1-B8/G8) -> 0
A9: Lei do bairro | B9: =COUNTIFS(Revisão!$D$2:$D$804,$A9,Revisão!$I$2:$I$804,B$3) -> 24 | C9: =COUNTIFS(Revisão!$D$2:$D$804,$A9,Revisão!$I$2:$I$804,C$3) -> 0 | D9: =COUNTIFS(Revisão!$D$2:$D$804,$A9,Revisão!$I$2:$I$804,D$3) -> 0 | E9: =COUNTIFS(Revisão!$D$2:$D$804,$A9,Revisão!$I$2:$I$804,E$3) -> 0 | F9: =COUNTIFS(Revisão!$D$2:$D$804,$A9,Revisão!$I$2:$I$804,F$3) -> 0 | G9: =COUNTIF(Revisão!$D$2:$D$804,$A9) -> 24 | H9: =IF(G9=0,0,1-B9/G9) -> 0
A10: Projeto de lei | B10: =COUNTIFS(Revisão!$D$2:$D$804,$A10,Revisão!$I$2:$I$804,B$3) -> 9 | C10: =COUNTIFS(Revisão!$D$2:$D$804,$A10,Revisão!$I$2:$I$804,C$3) -> 0 | D10: =COUNTIFS(Revisão!$D$2:$D$804,$A10,Revisão!$I$2:$I$804,D$3) -> 0 | E10: =COUNTIFS(Revisão!$D$2:$D$804,$A10,Revisão!$I$2:$I$804,E$3) -> 0 | F10: =COUNTIFS(Revisão!$D$2:$D$804,$A10,Revisão!$I$2:$I$804,F$3) -> 0 | G10: =COUNTIF(Revisão!$D$2:$D$804,$A10) -> 9 | H10: =IF(G10=0,0,1-B10/G10) -> 0
A11: Ocorrência | B11: =COUNTIFS(Revisão!$D$2:$D$804,$A11,Revisão!$I$2:$I$804,B$3) -> 5 | C11: =COUNTIFS(Revisão!$D$2:$D$804,$A11,Revisão!$I$2:$I$804,C$3) -> 0 | D11: =COUNTIFS(Revisão!$D$2:$D$804,$A11,Revisão!$I$2:$I$804,D$3) -> 0 | E11: =COUNTIFS(Revisão!$D$2:$D$804,$A11,Revisão!$I$2:$I$804,E$3) -> 0 | F11: =COUNTIFS(Revisão!$D$2:$D$804,$A11,Revisão!$I$2:$I$804,F$3) -> 0 | G11: =COUNTIF(Revisão!$D$2:$D$804,$A11) -> 5 | H11: =IF(G11=0,0,1-B11/G11) -> 0
A12: Dica de lei do evento | B12: =COUNTIFS(Revisão!$D$2:$D$804,$A12,Revisão!$I$2:$I$804,B$3) -> 5 | C12: =COUNTIFS(Revisão!$D$2:$D$804,$A12,Revisão!$I$2:$I$804,C$3) -> 0 | D12: =COUNTIFS(Revisão!$D$2:$D$804,$A12,Revisão!$I$2:$I$804,D$3) -> 0 | E12: =COUNTIFS(Revisão!$D$2:$D$804,$A12,Revisão!$I$2:$I$804,E$3) -> 0 | F12: =COUNTIFS(Revisão!$D$2:$D$804,$A12,Revisão!$I$2:$I$804,F$3) -> 0 | G12: =COUNTIF(Revisão!$D$2:$D$804,$A12) -> 5 | H12: =IF(G12=0,0,1-B12/G12) -> 0
A13: Audiência no Fórum | B13: =COUNTIFS(Revisão!$D$2:$D$804,$A13,Revisão!$I$2:$I$804,B$3) -> 5 | C13: =COUNTIFS(Revisão!$D$2:$D$804,$A13,Revisão!$I$2:$I$804,C$3) -> 0 | D13: =COUNTIFS(Revisão!$D$2:$D$804,$A13,Revisão!$I$2:$I$804,D$3) -> 0 | E13: =COUNTIFS(Revisão!$D$2:$D$804,$A13,Revisão!$I$2:$I$804,E$3) -> 0 | F13: =COUNTIFS(Revisão!$D$2:$D$804,$A13,Revisão!$I$2:$I$804,F$3) -> 0 | G13: =COUNTIF(Revisão!$D$2:$D$804,$A13) -> 5 | H13: =IF(G13=0,0,1-B13/G13) -> 0
A14: Descrição | B14: =COUNTIFS(Revisão!$D$2:$D$804,$A14,Revisão!$I$2:$I$804,B$3) -> 4 | C14: =COUNTIFS(Revisão!$D$2:$D$804,$A14,Revisão!$I$2:$I$804,C$3) -> 0 | D14: =COUNTIFS(Revisão!$D$2:$D$804,$A14,Revisão!$I$2:$I$804,D$3) -> 0 | E14: =COUNTIFS(Revisão!$D$2:$D$804,$A14,Revisão!$I$2:$I$804,E$3) -> 0 | F14: =COUNTIFS(Revisão!$D$2:$D$804,$A14,Revisão!$I$2:$I$804,F$3) -> 0 | G14: =COUNTIF(Revisão!$D$2:$D$804,$A14) -> 4 | H14: =IF(G14=0,0,1-B14/G14) -> 0
A15: Total | B15: =SUM(B4:B14) -> 803 | C15: =SUM(C4:C14) -> 0 | D15: =SUM(D4:D14) -> 0 | E15: =SUM(E4:E14) -> 0 | F15: =SUM(F4:F14) -> 0 | G15: =SUM(G4:G14) -> 803 | H15: =IF(G15=0,0,1-B15/G15) -> 0
A17: Itens com prioridade Alta ainda a revisar | B17: =COUNTIFS(Revisão!$G$2:$G$804,"Alta",Revisão!$I$2:$I$804,"A revisar") -> 350
A18: Itens marcados em "Atenção" ainda a revisar | B18: =COUNTIFS(Revisão!$H$2:$H$804,"?*",Revisão!$I$2:$I$804,"A revisar") -> 42
